{
  "title": "Red Dead Redemption 2 Edit 🔥 #shorts #rdr2 #gaming",
  "description": "Red Dead Redemption 2 Edit 🎮✨ #shorts #rdr2 #arthurmorgan #reddeadredemption2 #gaming #edit #viral #ps5 #ps4 #aesthetic #fyp #foryou #foryoupage #trending #youtubeshorts #gamingedit #rdr2edit #arthurmorganedit #dutchvanlinde #johnmarston #openworld #western #cowboy #rockstargames #actiongame #ps5gameplay #gamingshorts #epicgaming #playstation #xbox #videogames #gamers #gamer #viralshorts #aestheticedit #gameredit #gamingcommunity #outlaw #wild west #outlawgang",
  "playlist": "",
  "category": "20",
  "tags": [
    "rdr2",
    "arthurmorgan",
    "reddeadredemption2",
    "shorts",
    "gaming",
    "edit",
    "viral",
    "fyp",
    "foryou",
    "ps4",
    "ps5",
    "western",
    "aesthetic",
    "gamingedit",
    "rdr2edit",
    "arthurmorganedit",
    "gamingshorts",
    "youtubeshorts",
    "trending",
    "epicgaming",
    "foryoupage",
    "gameredit",
    "playstation",
    "xbox",
    "actiongame",
    "videogames",
    "gamers",
    "viralshorts",
    "aestheticedit",
    "openworld",
    "cowboy",
    "rockstargames",
    "dutchvanlinde",
    "johnmarston",
    "outlaw",
    "wildwest",
    "ps5gameplay",
    "gamingcommunity",
    "openworldgame",
    "outlawgang"
  ]
}
